spynnaker_visualisers/__init__.py
spynnaker_visualisers/_bigsurhack.py
spynnaker_visualisers/_version.py
spynnaker_visualisers/glut_framework.py
spynnaker_visualisers/opengl_support.py
spynnaker_visualisers/raytrace/__init__.py
spynnaker_visualisers/raytrace/drawer.py
spynnaker_visualisers/sudoku/__init__.py
spynnaker_visualisers/sudoku/sudoku_visualiser.py
spynnaker_visualisers-1!7.4.1.dist-info/licenses/LICENSE
spynnaker_visualisers-1!7.4.1.dist-info/licenses/LICENSE_POLICY.md
spynnaker_visualisers-1!7.4.1.dist-info/METADATA
spynnaker_visualisers-1!7.4.1.dist-info/WHEEL
spynnaker_visualisers-1!7.4.1.dist-info/top_level.txt
spynnaker_visualisers-1!7.4.1.dist-info/zip-safe
spynnaker_visualisers-1!7.4.1.dist-info/RECORD
