Metadata-Version: 2.4
Name: sPyNNaker_visualisers
Version: 1!7.4.1
Summary: Visualisation clients for special sPyNNaker networks.
Home-page: https://github.com/SpiNNakerManchester/sPyNNakerVisualisersn
Maintainer: SpiNNakerTeam
Maintainer-email: spinnakerusers@googlegroups.com
License: Apache-2.0
Keywords: spinnaker,visualiser
Classifier: Development Status :: 5 - Production/Stable
Classifier: Intended Audience :: Developers
Classifier: Intended Audience :: Science/Research
Classifier: Natural Language :: English
Classifier: Operating System :: POSIX :: Linux
Classifier: Operating System :: Microsoft :: Windows
Classifier: Operating System :: MacOS
Classifier: Programming Language :: Python :: 3
Classifier: Programming Language :: Python :: 3.8
Classifier: Programming Language :: Python :: 3.9
Classifier: Programming Language :: Python :: 3.10
Classifier: Programming Language :: Python :: 3.11
Classifier: Programming Language :: Python :: 3.12
Requires-Python: <4,>=3.8
License-File: LICENSE
License-File: LICENSE_POLICY.md
Requires-Dist: PyOpenGL
Requires-Dist: SpiNNFrontEndCommon==1!7.4.1
Provides-Extra: test
Requires-Dist: flake8; extra == "test"
Requires-Dist: pylint; extra == "test"
Dynamic: license-file
